hanna_cloud/__init__.py
hanna_cloud/client.py
hanna_cloud-0.0.7.dist-info/licenses/LICENSE
hanna_cloud-0.0.7.dist-info/METADATA
hanna_cloud-0.0.7.dist-info/WHEEL
hanna_cloud-0.0.7.dist-info/top_level.txt
hanna_cloud-0.0.7.dist-info/RECORD
